phase_stitcher/__init__.py
phase_stitcher/__main__.py
phase_stitcher/args_builder.py
phase_stitcher/args_extractor.py
phase_stitcher/compute_stats.py
phase_stitcher/compute_transition.py
phase_stitcher/phase_stitcher.py
phase_stitcher/phaser.py
phase_stitcher/utils.py
phase_stitcher-0.0.3.dist-info/METADATA
phase_stitcher-0.0.3.dist-info/WHEEL
phase_stitcher-0.0.3.dist-info/entry_points.txt
phase_stitcher-0.0.3.dist-info/top_level.txt
phase_stitcher-0.0.3.dist-info/RECORD
