Metadata-Version: 2.1
Name: phase-stitcher
Version: 0.0.3
Summary: a python program to stitch the ReadBack phased haplotypes in F1 hybrids.
Home-page: https://github.com/everestial/pHASE-Stitcher
Author: Bishwa K. Giri
Author-email: kirannbishwa01@gmail.com
License: UNKNOWN
Project-URL: Bug Tracker, https://github.com/everestial/pHASE-Stitcher
Platform: UNKNOWN
Classifier: Programming Language :: Python :: 3
Classifier: License :: OSI Approved :: MIT License
Classifier: Operating System :: OS Independent
Requires-Python: >=3.7
Requires-Dist: numpy (>=1.22)
Requires-Dist: matplotlib (>=3)
Requires-Dist: pandas (>=1)
Requires-Dist: dask (>=2021)
